{
  "Id": {
    "Id": "hades"
  },
  "Name": "Hades",
  "Stats": [
    {
      "Id": {
        "Id": "achieved"
      },
      "Name": "Achievement Unlocked",
      "Type": 1
    },
    {
      "Id": {
        "Id": "aegis_aspect_beowulf"
      },
      "Name": "Aspect of Beowul Rank",
      "Type": 2,
      "Min": 0,
      "Max": 5
    },
    {
      "Id": {
        "Id": "aegis_aspect_chaos"
      },
      "Name": "Aspect of Chaos Rank",
      "Type": 2,
      "Min": 0,
      "Max": 5
    },
    {
      "Id": {
        "Id": "aegis_aspect_zagreus"
      },
      "Name": "Aspect of Zagreus Rank",
      "Type": 2,
      "Min": 0,
      "Max": 5
    },
    {
      "Id": {
        "Id": "aegis_aspect_zeus"
      },
      "Name": "Aspect of Zeus Rank",
      "Type": 2,
      "Min": 0,
      "Max": 5
    },
    {
      "Id": {
        "Id": "coronacht_aspect_chiron"
      },
      "Name": "Aspect of Chiron Rank",
      "Type": 2,
      "Min": 0,
      "Max": 5
    },
    {
      "Id": {
        "Id": "coronacht_aspect_hera"
      },
      "Name": "Aspect of Hera Rank",
      "Type": 2,
      "Min": 0,
      "Max": 5
    },
    {
      "Id": {
        "Id": "coronacht_aspect_rama"
      },
      "Name": "Aspect of Rama Rank",
      "Type": 2,
      "Min": 0,
      "Max": 5
    },
    {
      "Id": {
        "Id": "coronacht_aspect_zagreus"
      },
      "Name": "Aspect of Zagreus Rank",
      "Type": 2,
      "Min": 0,
      "Max": 5
    },
    {
      "Id": {
        "Id": "exagryph_aspect_eris"
      },
      "Name": "Aspect of Eris Rank",
      "Type": 2,
      "Min": 0,
      "Max": 5
    },
    {
      "Id": {
        "Id": "exagryph_aspect_hestia"
      },
      "Name": "Aspect of Hestia Rank",
      "Type": 2,
      "Min": 0,
      "Max": 5
    },
    {
      "Id": {
        "Id": "exagryph_aspect_lucifer"
      },
      "Name": "Aspect of Lucifer Rank",
      "Type": 2,
      "Min": 0,
      "Max": 5
    },
    {
      "Id": {
        "Id": "exagryph_aspect_zagreus"
      },
      "Name": "Aspect of Zagreus Rank",
      "Type": 2,
      "Min": 0,
      "Max": 5
    },
    {
      "Id": {
        "Id": "keepsake_rank"
      },
      "Name": "Rank",
      "Type": 2,
      "Min": 1,
      "Max": 3
    },
    {
      "Id": {
        "Id": "malphon_aspect_demeter"
      },
      "Name": "Aspect of Demeter Rank",
      "Type": 2,
      "Min": 0,
      "Max": 5
    },
    {
      "Id": {
        "Id": "malphon_aspect_gilgamesh"
      },
      "Name": "Aspect of Gilgamesh Rank",
      "Type": 2,
      "Min": 0,
      "Max": 5
    },
    {
      "Id": {
        "Id": "malphon_aspect_talos"
      },
      "Name": "Aspect of Talos Rank",
      "Type": 2,
      "Min": 0,
      "Max": 5
    },
    {
      "Id": {
        "Id": "malphon_aspect_zagreus"
      },
      "Name": "Aspect of Zagreus Rank",
      "Type": 2,
      "Min": 0,
      "Max": 5
    },
    {
      "Id": {
        "Id": "prophecy_fulfilled"
      },
      "Name": "Fulfilled",
      "Type": 1
    },
    {
      "Id": {
        "Id": "stygius_aspect_arthur"
      },
      "Name": "Aspect of Arthur Rank",
      "Type": 2,
      "Min": 0,
      "Max": 5
    },
    {
      "Id": {
        "Id": "stygius_aspect_nemesis"
      },
      "Name": "Aspect of Nemesis Rank",
      "Type": 2,
      "Min": 0,
      "Max": 5
    },
    {
      "Id": {
        "Id": "stygius_aspect_poseidon"
      },
      "Name": "Aspect of Poseidon Rank",
      "Type": 2,
      "Min": 0,
      "Max": 5
    },
    {
      "Id": {
        "Id": "stygius_aspect_zagreus"
      },
      "Name": "Aspect of Zagreus Rank",
      "Type": 2,
      "Min": 0,
      "Max": 5
    },
    {
      "Id": {
        "Id": "unlocked"
      },
      "Name": "Unlocked",
      "Type": 1
    },
    {
      "Id": {
        "Id": "varatha_aspect_achilles"
      },
      "Name": "Aspect of Achilles Rank",
      "Type": 2,
      "Min": 0,
      "Max": 5
    },
    {
      "Id": {
        "Id": "varatha_aspect_guan_yu"
      },
      "Name": "Aspect of Guan Yu Rank",
      "Type": 2,
      "Min": 0,
      "Max": 5
    },
    {
      "Id": {
        "Id": "varatha_aspect_hades"
      },
      "Name": "Aspect of Hades Rank",
      "Type": 2,
      "Min": 0,
      "Max": 5
    },
    {
      "Id": {
        "Id": "varatha_aspect_zagreus"
      },
      "Name": "Aspect of Zagreus Rank",
      "Type": 2,
      "Min": 0,
      "Max": 5
    }
  ],
  "Classes": [
    {
      "Id": {
        "Id": "achievement"
      },
      "Stats": [
        {
          "Id": "achieved"
        }
      ]
    },
    {
      "Id": {
        "Id": "infernal_arm"
      },
      "Stats": [
        {
          "Id": "unlocked"
        }
      ]
    },
    {
      "Id": {
        "Id": "keepsake"
      },
      "Stats": [
        {
          "Id": "unlocked"
        },
        {
          "Id": "keepsake_rank"
        }
      ]
    },
    {
      "Id": {
        "Id": "prophecy"
      },
      "Stats": [
        {
          "Id": "prophecy_fulfilled"
        }
      ]
    }
  ],
  "Entities": [
    {
      "Id": {
        "Id": "a_friendly_wager"
      },
      "Name": "A Friendly Wager",
      "Class": {
        "Id": "prophecy"
      },
      "Stats": []
    },
    {
      "Id": {
        "Id": "a_place_of_revelry"
      },
      "Name": "A Place of Revelry",
      "Class": {
        "Id": "prophecy"
      },
      "Stats": []
    },
    {
      "Id": {
        "Id": "a_simple_job"
      },
      "Name": "A Simple Job",
      "Class": {
        "Id": "prophecy"
      },
      "Stats": []
    },
    {
      "Id": {
        "Id": "a_violent_past"
      },
      "Name": "A Violent Past",
      "Class": {
        "Id": "prophecy"
      },
      "Stats": []
    },
    {
      "Id": {
        "Id": "adamant_arrowhead"
      },
      "Name": "Adamant Arrowhead",
      "Class": {
        "Id": "keepsake"
      },
      "Stats": []
    },
    {
      "Id": {
        "Id": "aegis"
      },
      "Name": "Aegis",
      "Class": {
        "Id": "infernal_arm"
      },
      "Stats": [
        {
          "Id": "aegis_aspect_zagreus"
        },
        {
          "Id": "aegis_aspect_chaos"
        },
        {
          "Id": "aegis_aspect_zeus"
        },
        {
          "Id": "aegis_aspect_beowulf"
        }
      ]
    },
    {
      "Id": {
        "Id": "amusing_chaos"
      },
      "Name": "Amusing Chaos",
      "Class": {
        "Id": "prophecy"
      },
      "Stats": []
    },
    {
      "Id": {
        "Id": "arms_collector"
      },
      "Name": "Arms Collector",
      "Class": {
        "Id": "achievement"
      },
      "Stats": []
    },
    {
      "Id": {
        "Id": "back_to_work"
      },
      "Name": "Back to Work",
      "Class": {
        "Id": "achievement"
      },
      "Stats": []
    },
    {
      "Id": {
        "Id": "bad_call"
      },
      "Name": "Bad Call",
      "Class": {
        "Id": "achievement"
      },
      "Stats": []
    },
    {
      "Id": {
        "Id": "black_shawl"
      },
      "Name": "Black Shawl",
      "Class": {
        "Id": "keepsake"
      },
      "Stats": []
    },
    {
      "Id": {
        "Id": "blessed_by_the_gods"
      },
      "Name": "Blessed by the Gods",
      "Class": {
        "Id": "achievement"
      },
      "Stats": []
    },
    {
      "Id": {
        "Id": "blood_bound"
      },
      "Name": "Blood Bound",
      "Class": {
        "Id": "achievement"
      },
      "Stats": []
    },
    {
      "Id": {
        "Id": "blood_filled_vial"
      },
      "Name": "Blood-Filled Vial",
      "Class": {
        "Id": "keepsake"
      },
      "Stats": []
    },
    {
      "Id": {
        "Id": "bone_hourglass"
      },
      "Name": "Bone Hourglass",
      "Class": {
        "Id": "keepsake"
      },
      "Stats": []
    },
    {
      "Id": {
        "Id": "broken_spearpoint"
      },
      "Name": "Broken Spearpoint",
      "Class": {
        "Id": "keepsake"
      },
      "Stats": []
    },
    {
      "Id": {
        "Id": "champion_of_elysium"
      },
      "Name": "Champion of Elysium",
      "Class": {
        "Id": "achievement"
      },
      "Stats": []
    },
    {
      "Id": {
        "Id": "chthonic_coin_purse"
      },
      "Name": "Chthonic Coin Purse",
      "Class": {
        "Id": "keepsake"
      },
      "Stats": []
    },
    {
      "Id": {
        "Id": "chthonic_colleagues"
      },
      "Name": "Chthonic Colleagues",
      "Class": {
        "Id": "achievement"
      },
      "Stats": []
    },
    {
      "Id": {
        "Id": "chthonic_colleagues_fate"
      },
      "Name": "Chthonic Colleagues (Fate)",
      "Class": {
        "Id": "prophecy"
      },
      "Stats": []
    },
    {
      "Id": {
        "Id": "chthonic_knowledge"
      },
      "Name": "Chthonic Knowledge",
      "Class": {
        "Id": "prophecy"
      },
      "Stats": []
    },
    {
      "Id": {
        "Id": "close_at_heart"
      },
      "Name": "Close at Heart",
      "Class": {
        "Id": "prophecy"
      },
      "Stats": []
    },
    {
      "Id": {
        "Id": "complete_set"
      },
      "Name": "Complete Set",
      "Class": {
        "Id": "achievement"
      },
      "Stats": []
    },
    {
      "Id": {
        "Id": "conch_shell"
      },
      "Name": "Conch Shell",
      "Class": {
        "Id": "keepsake"
      },
      "Stats": []
    },
    {
      "Id": {
        "Id": "coronacht"
      },
      "Name": "Coronacht",
      "Class": {
        "Id": "infernal_arm"
      },
      "Stats": [
        {
          "Id": "coronacht_aspect_zagreus"
        },
        {
          "Id": "coronacht_aspect_chiron"
        },
        {
          "Id": "coronacht_aspect_hera"
        },
        {
          "Id": "coronacht_aspect_rama"
        }
      ]
    },
    {
      "Id": {
        "Id": "cosmic_egg"
      },
      "Name": "Cosmic Egg",
      "Class": {
        "Id": "keepsake"
      },
      "Stats": []
    },
    {
      "Id": {
        "Id": "customer_loyalty"
      },
      "Name": "Customer Loyalty",
      "Class": {
        "Id": "prophecy"
      },
      "Stats": []
    },
    {
      "Id": {
        "Id": "dark_reflections"
      },
      "Name": "Dark Reflections",
      "Class": {
        "Id": "achievement"
      },
      "Stats": []
    },
    {
      "Id": {
        "Id": "dark_reflections_fate"
      },
      "Name": "Dark Reflections (Fate)",
      "Class": {
        "Id": "prophecy"
      },
      "Stats": []
    },
    {
      "Id": {
        "Id": "day_or_night_trader"
      },
      "Name": "Day-or-Night Trader",
      "Class": {
        "Id": "achievement"
      },
      "Stats": []
    },
    {
      "Id": {
        "Id": "death_dealer"
      },
      "Name": "Death Dealer",
      "Class": {
        "Id": "achievement"
      },
      "Stats": []
    },
    {
      "Id": {
        "Id": "denizens_of_the_deep"
      },
      "Name": "Denizens of the Deep",
      "Class": {
        "Id": "prophecy"
      },
      "Stats": []
    },
    {
      "Id": {
        "Id": "distant_memory"
      },
      "Name": "Distant Memory",
      "Class": {
        "Id": "keepsake"
      },
      "Stats": []
    },
    {
      "Id": {
        "Id": "distant_relatives"
      },
      "Name": "Distant Relatives",
      "Class": {
        "Id": "prophecy"
      },
      "Stats": []
    },
    {
      "Id": {
        "Id": "divided_by_death"
      },
      "Name": "Divided by Death",
      "Class": {
        "Id": "achievement"
      },
      "Stats": []
    },
    {
      "Id": {
        "Id": "divided_by_death_fate"
      },
      "Name": "Divided by Death (Fate)",
      "Class": {
        "Id": "prophecy"
      },
      "Stats": []
    },
    {
      "Id": {
        "Id": "divine_pairings"
      },
      "Name": "Divine Pairings",
      "Class": {
        "Id": "prophecy"
      },
      "Stats": []
    },
    {
      "Id": {
        "Id": "end_to_torment"
      },
      "Name": "End to Torment",
      "Class": {
        "Id": "achievement"
      },
      "Stats": []
    },
    {
      "Id": {
        "Id": "end_to_torment_fate"
      },
      "Name": "End To Torment (Fate)",
      "Class": {
        "Id": "prophecy"
      },
      "Stats": []
    },
    {
      "Id": {
        "Id": "escaped_asphodel"
      },
      "Name": "Escaped Asphodel",
      "Class": {
        "Id": "achievement"
      },
      "Stats": []
    },
    {
      "Id": {
        "Id": "escaped_elysium"
      },
      "Name": "Escaped Elysium",
      "Class": {
        "Id": "achievement"
      },
      "Stats": []
    },
    {
      "Id": {
        "Id": "escaped_tartarus"
      },
      "Name": "Escaped Tartarus",
      "Class": {
        "Id": "achievement"
      },
      "Stats": []
    },
    {
      "Id": {
        "Id": "eternal_rest"
      },
      "Name": "Eternal Rest",
      "Class": {
        "Id": "prophecy"
      },
      "Stats": []
    },
    {
      "Id": {
        "Id": "eternal_rose"
      },
      "Name": "Eternal Rose",
      "Class": {
        "Id": "keepsake"
      },
      "Stats": []
    },
    {
      "Id": {
        "Id": "evergreen_acorn"
      },
      "Name": "Evergreen Acorn",
      "Class": {
        "Id": "keepsake"
      },
      "Stats": []
    },
    {
      "Id": {
        "Id": "exagryph"
      },
      "Name": "Exagryph",
      "Class": {
        "Id": "infernal_arm"
      },
      "Stats": [
        {
          "Id": "exagryph_aspect_zagreus"
        },
        {
          "Id": "exagryph_aspect_eris"
        },
        {
          "Id": "exagryph_aspect_hestia"
        },
        {
          "Id": "exagryph_aspect_lucifer"
        }
      ]
    },
    {
      "Id": {
        "Id": "family_reunion"
      },
      "Name": "Family Reunion",
      "Class": {
        "Id": "prophecy"
      },
      "Stats": []
    },
    {
      "Id": {
        "Id": "friends_forever"
      },
      "Name": "Friends Forever",
      "Class": {
        "Id": "achievement"
      },
      "Stats": []
    },
    {
      "Id": {
        "Id": "friends_in_high_places"
      },
      "Name": "Friends in High Places",
      "Class": {
        "Id": "achievement"
      },
      "Stats": []
    },
    {
      "Id": {
        "Id": "frostbitten_horn"
      },
      "Name": "Frostbitten Horn",
      "Class": {
        "Id": "keepsake"
      },
      "Stats": []
    },
    {
      "Id": {
        "Id": "god_of_swiftness"
      },
      "Name": "God of Swiftness",
      "Class": {
        "Id": "prophecy"
      },
      "Stats": []
    },
    {
      "Id": {
        "Id": "god_of_the_heavens"
      },
      "Name": "God of the Heavens",
      "Class": {
        "Id": "prophecy"
      },
      "Stats": []
    },
    {
      "Id": {
        "Id": "god_of_the_sea"
      },
      "Name": "God of the Sea",
      "Class": {
        "Id": "prophecy"
      },
      "Stats": []
    },
    {
      "Id": {
        "Id": "god_of_war"
      },
      "Name": "God of War",
      "Class": {
        "Id": "prophecy"
      },
      "Stats": []
    },
    {
      "Id": {
        "Id": "god_of_wine"
      },
      "Name": "God of Wine",
      "Class": {
        "Id": "prophecy"
      },
      "Stats": []
    },
    {
      "Id": {
        "Id": "goddess_of_love"
      },
      "Name": "Goddess of Love",
      "Class": {
        "Id": "prophecy"
      },
      "Stats": []
    },
    {
      "Id": {
        "Id": "goddess_of_seasons"
      },
      "Name": "Goddess of Seasons",
      "Class": {
        "Id": "prophecy"
      },
      "Stats": []
    },
    {
      "Id": {
        "Id": "goddess_of_the_hunt"
      },
      "Name": "Goddess of the Hunt",
      "Class": {
        "Id": "prophecy"
      },
      "Stats": []
    },
    {
      "Id": {
        "Id": "goddess_of_wisdom"
      },
      "Name": "Goddess of Wisdom",
      "Class": {
        "Id": "prophecy"
      },
      "Stats": []
    },
    {
      "Id": {
        "Id": "grown_close"
      },
      "Name": "Grown Close",
      "Class": {
        "Id": "achievement"
      },
      "Stats": []
    },
    {
      "Id": {
        "Id": "had_to_happen"
      },
      "Name": "Had to Happen",
      "Class": {
        "Id": "achievement"
      },
      "Stats": []
    },
    {
      "Id": {
        "Id": "harpy_feather_duster"
      },
      "Name": "Harpy Feather Duster",
      "Class": {
        "Id": "keepsake"
      },
      "Stats": []
    },
    {
      "Id": {
        "Id": "harsh_conditions"
      },
      "Name": "Harsh Conditions",
      "Class": {
        "Id": "achievement"
      },
      "Stats": []
    },
    {
      "Id": {
        "Id": "harsh_conditions_fate"
      },
      "Name": "Harsh Conditions (Fate)",
      "Class": {
        "Id": "prophecy"
      },
      "Stats": []
    },
    {
      "Id": {
        "Id": "haste_of_hermes"
      },
      "Name": "Haste of Hermes",
      "Class": {
        "Id": "achievement"
      },
      "Stats": []
    },
    {
      "Id": {
        "Id": "hold_the_onions"
      },
      "Name": "Hold the Onions",
      "Class": {
        "Id": "achievement"
      },
      "Stats": []
    },
    {
      "Id": {
        "Id": "home_makeover"
      },
      "Name": "Home Makeover",
      "Class": {
        "Id": "achievement"
      },
      "Stats": []
    },
    {
      "Id": {
        "Id": "infernal_arms"
      },
      "Name": "Infernal Arms",
      "Class": {
        "Id": "achievement"
      },
      "Stats": []
    },
    {
      "Id": {
        "Id": "infernal_arms_fate"
      },
      "Name": "Infernal Arms (Fate)",
      "Class": {
        "Id": "prophecy"
      },
      "Stats": []
    },
    {
      "Id": {
        "Id": "is_there_no_escape"
      },
      "Name": "Is There No Escape?",
      "Class": {
        "Id": "achievement"
      },
      "Stats": []
    },
    {
      "Id": {
        "Id": "is_there_no_escape_fate"
      },
      "Name": "Is There No Escape? (Fate)",
      "Class": {
        "Id": "prophecy"
      },
      "Stats": []
    },
    {
      "Id": {
        "Id": "lambent_plume"
      },
      "Name": "Lambent Plume",
      "Class": {
        "Id": "keepsake"
      },
      "Stats": []
    },
    {
      "Id": {
        "Id": "lucky_tooth"
      },
      "Name": "Lucky Tooth",
      "Class": {
        "Id": "keepsake"
      },
      "Stats": []
    },
    {
      "Id": {
        "Id": "malphon"
      },
      "Name": "Malphon",
      "Class": {
        "Id": "infernal_arm"
      },
      "Stats": [
        {
          "Id": "malphon_aspect_zagreus"
        },
        {
          "Id": "malphon_aspect_talos"
        },
        {
          "Id": "malphon_aspect_demeter"
        },
        {
          "Id": "malphon_aspect_gilgamesh"
        }
      ]
    },
    {
      "Id": {
        "Id": "master_of_arms"
      },
      "Name": "Master of Arms",
      "Class": {
        "Id": "achievement"
      },
      "Stats": []
    },
    {
      "Id": {
        "Id": "master_of_arms_fate"
      },
      "Name": "Master of Arms (Fate)",
      "Class": {
        "Id": "prophecy"
      },
      "Stats": []
    },
    {
      "Id": {
        "Id": "musician_and_muse"
      },
      "Name": "Musician and Muse",
      "Class": {
        "Id": "achievement"
      },
      "Stats": []
    },
    {
      "Id": {
        "Id": "musician_and_muse_fate"
      },
      "Name": "Musician and Muse (Fate)",
      "Class": {
        "Id": "prophecy"
      },
      "Stats": []
    },
    {
      "Id": {
        "Id": "myrmidon_bracer"
      },
      "Name": "Myrmidon Bracer",
      "Class": {
        "Id": "keepsake"
      },
      "Stats": []
    },
    {
      "Id": {
        "Id": "night_and_darkness"
      },
      "Name": "Night and Darkness",
      "Class": {
        "Id": "achievement"
      },
      "Stats": []
    },
    {
      "Id": {
        "Id": "night_and_darkness_fate"
      },
      "Name": "Night and Darkness (Fate)",
      "Class": {
        "Id": "prophecy"
      },
      "Stats": []
    },
    {
      "Id": {
        "Id": "nyxs_mirror"
      },
      "Name": "Nyx\u0027s Mirror",
      "Class": {
        "Id": "achievement"
      },
      "Stats": []
    },
    {
      "Id": {
        "Id": "old_spiked_collar"
      },
      "Name": "Old Spiked Collar",
      "Class": {
        "Id": "keepsake"
      },
      "Stats": []
    },
    {
      "Id": {
        "Id": "one_for_the_ages"
      },
      "Name": "One for the Ages",
      "Class": {
        "Id": "achievement"
      },
      "Stats": []
    },
    {
      "Id": {
        "Id": "overflowing_cup"
      },
      "Name": "Overflowing Cup",
      "Class": {
        "Id": "keepsake"
      },
      "Stats": []
    },
    {
      "Id": {
        "Id": "owl_pendant"
      },
      "Name": "Owl Pendant",
      "Class": {
        "Id": "keepsake"
      },
      "Stats": []
    },
    {
      "Id": {
        "Id": "pierced_butterfly"
      },
      "Name": "Pierced Butterfly",
      "Class": {
        "Id": "keepsake"
      },
      "Stats": []
    },
    {
      "Id": {
        "Id": "pom_blossom"
      },
      "Name": "Pom Blossom",
      "Class": {
        "Id": "keepsake"
      },
      "Stats": []
    },
    {
      "Id": {
        "Id": "power_without_equal"
      },
      "Name": "Power Without Equal",
      "Class": {
        "Id": "prophecy"
      },
      "Stats": []
    },
    {
      "Id": {
        "Id": "primordial_banes"
      },
      "Name": "Primordial Banes",
      "Class": {
        "Id": "prophecy"
      },
      "Stats": []
    },
    {
      "Id": {
        "Id": "primordial_boons"
      },
      "Name": "Primordial Boons",
      "Class": {
        "Id": "prophecy"
      },
      "Stats": []
    },
    {
      "Id": {
        "Id": "rare_collectible"
      },
      "Name": "Rare Collectible",
      "Class": {
        "Id": "achievement"
      },
      "Stats": []
    },
    {
      "Id": {
        "Id": "river_denizens"
      },
      "Name": "River Denizens",
      "Class": {
        "Id": "achievement"
      },
      "Stats": []
    },
    {
      "Id": {
        "Id": "sea_gods_spite"
      },
      "Name": "Sea-God\u0027s Spite",
      "Class": {
        "Id": "prophecy"
      },
      "Stats": []
    },
    {
      "Id": {
        "Id": "shattered_shackle"
      },
      "Name": "Shattered Shackle",
      "Class": {
        "Id": "keepsake"
      },
      "Stats": []
    },
    {
      "Id": {
        "Id": "sigil_of_the_dead"
      },
      "Name": "Sigil of the Dead",
      "Class": {
        "Id": "keepsake"
      },
      "Stats": []
    },
    {
      "Id": {
        "Id": "skelly_slayer"
      },
      "Name": "Skelly Slayer",
      "Class": {
        "Id": "achievement"
      },
      "Stats": []
    },
    {
      "Id": {
        "Id": "skellys_last_lamentations"
      },
      "Name": "Skelly\u0027s Last Lamentations",
      "Class": {
        "Id": "achievement"
      },
      "Stats": []
    },
    {
      "Id": {
        "Id": "skull_earring"
      },
      "Name": "Skull Earring",
      "Class": {
        "Id": "keepsake"
      },
      "Stats": []
    },
    {
      "Id": {
        "Id": "slashed_benefits"
      },
      "Name": "Slashed Benefits",
      "Class": {
        "Id": "achievement"
      },
      "Stats": []
    },
    {
      "Id": {
        "Id": "slashed_benefits_fate"
      },
      "Name": "Slashed Benefits (Fate)",
      "Class": {
        "Id": "prophecy"
      },
      "Stats": []
    },
    {
      "Id": {
        "Id": "something_from_everyone"
      },
      "Name": "Something From Everyone",
      "Class": {
        "Id": "achievement"
      },
      "Stats": []
    },
    {
      "Id": {
        "Id": "stygius"
      },
      "Name": "Stygius",
      "Class": {
        "Id": "infernal_arm"
      },
      "Stats": [
        {
          "Id": "stygius_aspect_zagreus"
        },
        {
          "Id": "stygius_aspect_nemesis"
        },
        {
          "Id": "stygius_aspect_poseidon"
        },
        {
          "Id": "stygius_aspect_arthur"
        }
      ]
    },
    {
      "Id": {
        "Id": "thanks_but_no_thanks"
      },
      "Name": "Thanks, But No Thanks",
      "Class": {
        "Id": "achievement"
      },
      "Stats": []
    },
    {
      "Id": {
        "Id": "the_adamant_rail"
      },
      "Name": "The Adamant Rail",
      "Class": {
        "Id": "prophecy"
      },
      "Stats": []
    },
    {
      "Id": {
        "Id": "the_dawn_bringer"
      },
      "Name": "The Dawn Bringer",
      "Class": {
        "Id": "prophecy"
      },
      "Stats": []
    },
    {
      "Id": {
        "Id": "the_dragons_rival"
      },
      "Name": "The Dragon\u0027s Rival",
      "Class": {
        "Id": "prophecy"
      },
      "Stats": []
    },
    {
      "Id": {
        "Id": "the_eternal_spear"
      },
      "Name": "The Eternal Spear",
      "Class": {
        "Id": "prophecy"
      },
      "Stats": []
    },
    {
      "Id": {
        "Id": "the_family_secret"
      },
      "Name": "The Family Secret",
      "Class": {
        "Id": "achievement"
      },
      "Stats": []
    },
    {
      "Id": {
        "Id": "the_fated_saint_of_war"
      },
      "Name": "The Fated Saint of War",
      "Class": {
        "Id": "prophecy"
      },
      "Stats": []
    },
    {
      "Id": {
        "Id": "the_gift_of_song"
      },
      "Name": "The Gift of Song",
      "Class": {
        "Id": "prophecy"
      },
      "Stats": []
    },
    {
      "Id": {
        "Id": "the_god_like_king"
      },
      "Name": "The God-like King",
      "Class": {
        "Id": "prophecy"
      },
      "Stats": []
    },
    {
      "Id": {
        "Id": "the_heart_seeking_bow"
      },
      "Name": "The Heart-Seeking Bow",
      "Class": {
        "Id": "prophecy"
      },
      "Stats": []
    },
    {
      "Id": {
        "Id": "the_holy_liege"
      },
      "Name": "The Holy Liege",
      "Class": {
        "Id": "prophecy"
      },
      "Stats": []
    },
    {
      "Id": {
        "Id": "the_preservers_avatar"
      },
      "Name": "The Preserver\u0027s Avatar",
      "Class": {
        "Id": "prophecy"
      },
      "Stats": []
    },
    {
      "Id": {
        "Id": "the_queens_plan"
      },
      "Name": "The Queen\u0027s Plan",
      "Class": {
        "Id": "prophecy"
      },
      "Stats": []
    },
    {
      "Id": {
        "Id": "the_reluctant_musician"
      },
      "Name": "The Reluctant Musician",
      "Class": {
        "Id": "prophecy"
      },
      "Stats": []
    },
    {
      "Id": {
        "Id": "the_shield_of_chaos"
      },
      "Name": "The Shield of Chaos",
      "Class": {
        "Id": "prophecy"
      },
      "Stats": []
    },
    {
      "Id": {
        "Id": "the_stygian_blade"
      },
      "Name": "The Stygian Blade",
      "Class": {
        "Id": "prophecy"
      },
      "Stats": []
    },
    {
      "Id": {
        "Id": "the_twin_fists"
      },
      "Name": "The Twin Fists",
      "Class": {
        "Id": "prophecy"
      },
      "Stats": []
    },
    {
      "Id": {
        "Id": "the_useless_trinket"
      },
      "Name": "The Useless Trinket",
      "Class": {
        "Id": "achievement"
      },
      "Stats": []
    },
    {
      "Id": {
        "Id": "the_useless_trinket_fate"
      },
      "Name": "The Useless Trinket (Fate)",
      "Class": {
        "Id": "prophecy"
      },
      "Stats": []
    },
    {
      "Id": {
        "Id": "thorn_of_thanatos"
      },
      "Name": "Thorn of Thanatos",
      "Class": {
        "Id": "achievement"
      },
      "Stats": []
    },
    {
      "Id": {
        "Id": "three_headed_boy"
      },
      "Name": "Three-Headed Boy",
      "Class": {
        "Id": "achievement"
      },
      "Stats": []
    },
    {
      "Id": {
        "Id": "thunder_signet"
      },
      "Name": "Thunder Signet",
      "Class": {
        "Id": "keepsake"
      },
      "Stats": []
    },
    {
      "Id": {
        "Id": "to_charons_credit"
      },
      "Name": "To Charon\u0027s Credit",
      "Class": {
        "Id": "achievement"
      },
      "Stats": []
    },
    {
      "Id": {
        "Id": "tools_of_the_architect"
      },
      "Name": "Tools of the Architect",
      "Class": {
        "Id": "achievement"
      },
      "Stats": []
    },
    {
      "Id": {
        "Id": "urge_to_sing"
      },
      "Name": "Urge to Sing",
      "Class": {
        "Id": "achievement"
      },
      "Stats": []
    },
    {
      "Id": {
        "Id": "varatha"
      },
      "Name": "Varatha",
      "Class": {
        "Id": "infernal_arm"
      },
      "Stats": [
        {
          "Id": "varatha_aspect_zagreus"
        },
        {
          "Id": "varatha_aspect_achilles"
        },
        {
          "Id": "varatha_aspect_hades"
        },
        {
          "Id": "varatha_aspect_guan_yu"
        }
      ]
    },
    {
      "Id": {
        "Id": "wanton_ransacking"
      },
      "Name": "Wanton Ransacking",
      "Class": {
        "Id": "prophecy"
      },
      "Stats": []
    },
    {
      "Id": {
        "Id": "war_gods_bloodlust"
      },
      "Name": "War-God\u0027s Bloodlust",
      "Class": {
        "Id": "achievement"
      },
      "Stats": []
    },
    {
      "Id": {
        "Id": "war_gods_bloodlust_fate"
      },
      "Name": "War-God\u0027s Bloodlust (Fate)",
      "Class": {
        "Id": "prophecy"
      },
      "Stats": []
    },
    {
      "Id": {
        "Id": "weapon_of_fate"
      },
      "Name": "Weapon of Fate",
      "Class": {
        "Id": "achievement"
      },
      "Stats": []
    },
    {
      "Id": {
        "Id": "well_stocked"
      },
      "Name": "Well Stocked",
      "Class": {
        "Id": "achievement"
      },
      "Stats": []
    },
    {
      "Id": {
        "Id": "well_versed"
      },
      "Name": "Well Versed",
      "Class": {
        "Id": "achievement"
      },
      "Stats": []
    }
  ],
  "Projects": [
    {
      "Name": "Fulfill all prophecies",
      "Objectives": [
        {
          "Name": "Fulfil all prophecies",
          "Requirements": [
            {
              "Class": {
                "Id": "prophecy"
              },
              "Stat": {
                "Id": "prophecy_fulfilled"
              },
              "Min": 1
            }
          ]
        }
      ]
    },
    {
      "Name": "Max all infernal arms",
      "Objectives": [
        {
          "Name": "Unlock all infernal arms",
          "Requirements": [
            {
              "Class": {
                "Id": "infernal_arm"
              },
              "Stat": {
                "Id": "unlocked"
              },
              "Min": 1
            }
          ]
        }
      ]
    },
    {
      "Name": "Max all keepsakes",
      "Objectives": [
        {
          "Name": "Unlock all keepsakes",
          "Requirements": [
            {
              "Class": {
                "Id": "keepsake"
              },
              "Stat": {
                "Id": "unlocked"
              },
              "Min": 1
            }
          ]
        },
        {
          "Name": "Rank all keepsakes to max rank",
          "Requirements": [
            {
              "Class": {
                "Id": "keepsake"
              },
              "Stat": {
                "Id": "keepsake_rank"
              },
              "Min": 3
            }
          ]
        }
      ]
    },
    {
      "Name": "Unlock all achievements",
      "Objectives": [
        {
          "Name": "Unlock all steam achievements",
          "Requirements": [
            {
              "Class": {
                "Id": "achievement"
              },
              "Stat": {
                "Id": "achieved"
              },
              "Min": 1
            }
          ]
        }
      ]
    }
  ]
}